{
  "fileName": "page_26",
  "words": [
    {
      "id": 1,
      "japanese": "ますます",
      "pronunciation": "ますます",
      "meaning": "점점"
    },
    {
      "id": 2,
      "japanese": "全然",
      "pronunciation": "ぜんぜん",
      "meaning": "전혀"
    },
    {
      "id": 3,
      "japanese": "英語がぺらぺらだ",
      "pronunciation": "えいごがぺらぺらだ",
      "meaning": "영어가 유창하다"
    },
    {
      "id": 4,
      "japanese": "がっかりする",
      "pronunciation": "がっかりする",
      "meaning": "실망하다, 낙담하다"
    },
    {
      "id": 5,
      "japanese": "学校をサボる",
      "pronunciation": "がっこうをサボる",
      "meaning": "학교를 빼먹다"
    },
    {
      "id": 6,
      "japanese": "まったく",
      "pronunciation": "まったく",
      "meaning": "완전히"
    },
    {
      "id": 7,
      "japanese": "約",
      "pronunciation": "やく",
      "meaning": "약"
    },
    {
      "id": 8,
      "japanese": "ようやく",
      "pronunciation": "ようやく",
      "meaning": "드디어"
    },
    {
      "id": 9,
      "japanese": "一番",
      "pronunciation": "いちばん",
      "meaning": "가장, 제일"
    },
    {
      "id": 10,
      "japanese": "だんだん",
      "pronunciation": "だんだん",
      "meaning": "점점"
    }
  ]
}
